lentach/__init__.py
lentach/client.py
lentach-0.0.1.dist-info/LICENSE
lentach-0.0.1.dist-info/METADATA
lentach-0.0.1.dist-info/WHEEL
lentach-0.0.1.dist-info/top_level.txt
lentach-0.0.1.dist-info/RECORD
