Metadata-Version: 2.1
Name: lentach
Version: 0.0.1
Summary: Fully asynchronous API wrapper for lenta.ru
Home-page: https://github.com/wkpn/lentach
Author: wkpn
License: MIT
Keywords: lenta.ru,лента,lentach,api,wrapper,async
Platform: UNKNOWN
Classifier: Development Status :: 1 - Planning
Classifier: Framework :: AsyncIO
Classifier: Intended Audience :: Developers
Classifier: License :: OSI Approved :: MIT License
Classifier: Programming Language :: Python :: 3.6
Classifier: Programming Language :: Python :: 3.7
Requires-Python: >=3.6
Requires-Dist: httpx (==0.11.1)
